ppdmod/__init__.py
ppdmod/base.py
ppdmod/components.py
ppdmod/data.py
ppdmod/fitting.py
ppdmod/options.py
ppdmod/parameter.py
ppdmod/plot.py
ppdmod/utils.py
ppdmod/config/standard_parameters.toml
ppdmod-2.1.0.dist-info/licenses/LICENSE
ppdmod-2.1.0.dist-info/METADATA
ppdmod-2.1.0.dist-info/WHEEL
ppdmod-2.1.0.dist-info/top_level.txt
ppdmod-2.1.0.dist-info/RECORD
