Metadata-Version: 2.4
Name: ppdmod
Version: 2.1.0
Summary: A package for modelling and model-fitting protoplanetary disks
Author-email: Marten Scheuck <code@mbscheuck.com>
License: MIT License
Project-URL: repository, https://codeberg.org/MBSck/ppdmod.git
Classifier: Framework :: Pytest
Classifier: Framework :: Sphinx
Classifier: License :: OSI Approved :: MIT License
Classifier: Natural Language :: English
Classifier: Operating System :: OS Independent
Classifier: Programming Language :: Python :: 3
Classifier: Programming Language :: Python :: 3.9
Classifier: Topic :: Scientific/Engineering :: Astronomy
Classifier: Topic :: Scientific/Engineering :: Physics
Requires-Python: >=3.11
License-File: LICENSE
Requires-Dist: astropy>=6.1.4
Requires-Dist: corner>=2.2.2
Requires-Dist: dynesty>=2.1.4
Requires-Dist: matplotlib>=3.9.2
Requires-Dist: numpy>=2.0.2
Requires-Dist: openpyxl>=3.1.5
Requires-Dist: pandas>=2.2.3
Requires-Dist: scipy>=1.14.1
Requires-Dist: toml>=0.10.2
Requires-Dist: tqdm>=4.67.1
Dynamic: license-file
